turu/snowflake/__init__.py
turu/snowflake/_key_pair.py
turu/snowflake/async_connection.py
turu/snowflake/async_cursor.py
turu/snowflake/connection.py
turu/snowflake/cursor.py
turu/snowflake/features.py
turu/snowflake/mock_async_connection.py
turu/snowflake/mock_async_cursor.py
turu/snowflake/mock_connection.py
turu/snowflake/mock_cursor.py
turu/snowflake/py.typed
turu/snowflake/record/__init__.py
turu/snowflake/record/async_record_cursor.py
turu/snowflake/record/record_cursor.py
turu_snowflake-0.13.2.dist-info/METADATA
turu_snowflake-0.13.2.dist-info/WHEEL
turu_snowflake-0.13.2.dist-info/RECORD
