Metadata-Version: 2.3
Name: turu-snowflake
Version: 0.13.2
Summary: snowflake adapter for turu
Author: yassun7010
Author-email: yassun7010@outlook.com
Requires-Python: >=3.9,<4.0
Classifier: Development Status :: 4 - Beta
Classifier: Intended Audience :: Developers
Classifier: License :: OSI Approved :: MIT License
Classifier: Programming Language :: Python :: 3
Classifier: Programming Language :: Python :: 3.9
Classifier: Programming Language :: Python :: 3.10
Classifier: Programming Language :: Python :: 3.11
Classifier: Programming Language :: Python :: 3.12
Classifier: Programming Language :: Python :: 3.13
Classifier: Programming Language :: Python :: 3 :: Only
Classifier: Programming Language :: SQL
Classifier: Topic :: Database
Classifier: Topic :: Scientific/Engineering :: Information Analysis
Classifier: Topic :: Software Development
Classifier: Topic :: Software Development :: Libraries
Classifier: Topic :: Software Development :: Libraries :: Application Frameworks
Classifier: Topic :: Software Development :: Libraries :: Python Modules
Provides-Extra: pandas
Provides-Extra: pandera
Requires-Dist: pandas (>=2.2.3,<3.0.0) ; extra == "pandas"
Requires-Dist: pandera (>=0.20.0,<0.21.0) ; extra == "pandera"
Requires-Dist: pyarrow (>=18.0.0,<19.0.0) ; extra == "pandas"
Requires-Dist: snowflake-connector-python (>=3.6.0,<4.0.0)
Requires-Dist: turu-core (==0.13.2)
Requires-Dist: typing-extensions (>=4.9.0,<5.0.0)
Project-URL: Repository, https://github.com/yassun7010/turu-py
